gooate/__init__.py
gooate/constant.py
gooate/gooate.py
gooate-2.1.4.dist-info/LICENSE
gooate-2.1.4.dist-info/METADATA
gooate-2.1.4.dist-info/WHEEL
gooate-2.1.4.dist-info/top_level.txt
gooate-2.1.4.dist-info/RECORD
