Metadata-Version: 2.1
Name: gooate
Version: 2.1.4
Summary: A free and unlimited python tool.
Home-page: https://github.com/z10mx7/gooate
Author: z10mx7
Author-email: z10mx7@protonmail.com
Maintainer: z10mx7
Maintainer-email: z10mx7@protonmail.com
License: MIT
Platform: all
Classifier: Development Status :: 5 - Production/Stable
Classifier: License :: OSI Approved :: MIT License
Classifier: Intended Audience :: Developers
Classifier: Natural Language :: English
Classifier: Operating System :: OS Independent
Classifier: Programming Language :: Python
Classifier: Programming Language :: Python :: 3
Classifier: Programming Language :: Python :: 3.6
Classifier: Programming Language :: Python :: Implementation :: CPython
Classifier: Programming Language :: Python :: Implementation :: PyPy
Classifier: Topic :: Internet
Classifier: Topic :: Software Development :: Libraries
Classifier: Topic :: Software Development :: Libraries :: Python Modules
Classifier: Topic :: Utilities
Classifier: Typing :: Typed
License-File: LICENSE
